JokerAPI/__init__.py
JokerAPI/auth/__init__.py
JokerAPI/auth/client.py
JokerAPI/endpoints/__init__.py
JokerAPI/endpoints/call.py
JokerAPI/enums/__init__.py
JokerAPI/enums/callback.py
JokerAPI/enums/endpoint.py
JokerAPI/enums/response.py
JokerAPI/exceptions/__init__.py
JokerAPI/exceptions/exceptions.py
JokerAPI/format/__init__.py
JokerSDK-0.0.43.dist-info/METADATA
JokerSDK-0.0.43.dist-info/WHEEL
JokerSDK-0.0.43.dist-info/top_level.txt
JokerSDK-0.0.43.dist-info/RECORD
