Metadata-Version: 2.1
Name: JokerSDK
Version: 0.0.43
Summary: A Simple SDK for Joker's Voice API.
Home-page: https://github.com/0x96e63/JokerSDK
Author: 0x96e63
